README.md
setup.cfg
setup.py
furystoolbox/__init__.py
furystoolbox/common.py
furystoolbox/const.py
furystoolbox/random.py
furystoolbox.egg-info/PKG-INFO
furystoolbox.egg-info/SOURCES.txt
furystoolbox.egg-info/dependency_links.txt
furystoolbox.egg-info/entry_points.txt
furystoolbox.egg-info/requires.txt
furystoolbox.egg-info/top_level.txt
furystoolbox/cli/__init__.py
furystoolbox/cli/cli.py
furystoolbox/cli/hass.py