Metadata-Version: 2.1
Name: furystoolbox
Version: 0.0.12
Summary: A collection of tools.
Home-page: https://github.com/ludeeus/furystoolbox
Author: Joakim Sorensen
Author-email: ludeeus@gmail.com
License: UNKNOWN
Platform: UNKNOWN
Classifier: Programming Language :: Python :: 3
Classifier: License :: OSI Approved :: MIT License
Classifier: Operating System :: OS Independent
